onefinity/__init__.py
onefinity/onefinity.py
onefinity/random_words.py
onefinity-0.9.dist-info/LICENSE
onefinity-0.9.dist-info/METADATA
onefinity-0.9.dist-info/WHEEL
onefinity-0.9.dist-info/entry_points.txt
onefinity-0.9.dist-info/RECORD
