Metadata-Version: 2.3
Name: onefinity
Version: 0.9
Summary: A simple python based number and word guessing game.
License: MIT
Author: Shvetank Dattatreya
Author-email: hello.shvetank@gmail.com
Requires-Python: >=3.10
Classifier: License :: OSI Approved :: MIT License
Classifier: Programming Language :: Python :: 3
Classifier: Programming Language :: Python :: 3.10
Classifier: Programming Language :: Python :: 3.11
Classifier: Programming Language :: Python :: 3.12
Classifier: Programming Language :: Python :: 3.13
